ShrutiAI/__init__.py
ShrutiAI/client.py
ShrutiAI/exceptions.py
shrutiai-1.0.1.dist-info/licenses/LICENSE
shrutiai-1.0.1.dist-info/METADATA
shrutiai-1.0.1.dist-info/WHEEL
shrutiai-1.0.1.dist-info/top_level.txt
shrutiai-1.0.1.dist-info/RECORD
