Metadata-Version: 2.4
Name: ShrutiAI
Version: 1.0.1
Summary: Python SDK for interacting with the shrutiAI API - your AI-powered assistant
Home-page: https://github.com/shrisai-tech/shruti-ai-sdk
Author: Shri Sai Technology
Author-email: Shri Sai Technology <support@sstus.net>
License: MIT License
Project-URL: Homepage, https://shruti.ai/
Project-URL: Documentation, https://shruti.ai/docs
Project-URL: Repository, https://github.com/shrisai-tech/shruti-ai-sdk
Project-URL: Bug Reports, https://github.com/shrisai-tech/shruti-ai-sdk/issues
Keywords: ai,chat,assistant,api,sdk,shruti,artificial-intelligence,chatbot,voice,location,otp,verification,image-analysis,document-processing,farming,travel,math,search,youtube
Classifier: Development Status :: 4 - Beta
Classifier: Intended Audience :: Developers
Classifier: License :: OSI Approved :: MIT License
Classifier: Operating System :: OS Independent
Classifier: Programming Language :: Python :: 3
Classifier: Programming Language :: Python :: 3.8
Classifier: Programming Language :: Python :: 3.9
Classifier: Programming Language :: Python :: 3.10
Classifier: Programming Language :: Python :: 3.11
Classifier: Programming Language :: Python :: 3.12
Classifier: Topic :: Software Development :: Libraries :: Python Modules
Classifier: Topic :: Communications :: Chat
Classifier: Topic :: Internet :: WWW/HTTP
Classifier: Topic :: Scientific/Engineering :: Artificial Intelligence
Requires-Python: >=3.8
License-File: LICENSE
Requires-Dist: requests>=2.25.0
Dynamic: author
Dynamic: home-page
Dynamic: license-file
Dynamic: requires-python
